Metadata-Version: 2.4
Name: webis-html
Version: 1.0.4
Summary: Webis HTML extraction tool
Author-email: Webis <webis@example.com>
Maintainer-email: Webis <webis@example.com>
License: MIT
Project-URL: Homepage, https://github.com/Webis/Webis
Project-URL: Bug Tracker, https://github.com/Webis/Webis/issues
Keywords: web,extraction,ai,content,html,scraping,deepseek,llm,text-processing
Classifier: Development Status :: 4 - Beta
Classifier: Intended Audience :: Developers
Classifier: License :: OSI Approved :: MIT License
Classifier: Programming Language :: Python :: 3
Classifier: Programming Language :: Python :: 3.8
Classifier: Programming Language :: Python :: 3.9
Classifier: Programming Language :: Python :: 3.10
Classifier: Programming Language :: Python :: 3.11
Requires-Python: >=3.8
License-File: LICENSE
Requires-Dist: beautifulsoup4>=4.12.0
Requires-Dist: gne>=0.3.0
Requires-Dist: joblib>=1.3.0
Requires-Dist: nltk>=3.8
Requires-Dist: numpy<2.0.0,>=1.23.5
Requires-Dist: pandas<2.0.0,>=1.5.0
Requires-Dist: requests>=2.28.0
Requires-Dist: scikit-learn>=1.3.0
Requires-Dist: tqdm>=4.65.0
Requires-Dist: trafilatura>=1.6.0
Requires-Dist: xgboost>=1.7.0
Requires-Dist: httpx>=0.24.0
Requires-Dist: fastapi>=0.100.0
Requires-Dist: uvicorn>=0.23.0
Requires-Dist: pydantic>=2.0.0
Requires-Dist: python-multipart>=0.0.6
Requires-Dist: aiofiles>=23.0.0
Requires-Dist: click>=8.0.0
Requires-Dist: pathlib2>=2.3.0; python_version < "3.4"
Dynamic: license-file
